HISTORY.rst
LICENSE
MANIFEST.in
README.md
README.rst
setup.cfg
setup.py
mayan/LICENSE
mayan/__init__.py
mayan/celery.py
mayan/conf.py
mayan/runtime.py
mayan/urls.py
mayan/wsgi.py
mayan/apps/__init__.py
mayan/apps/acls/__init__.py
mayan/apps/acls/admin.py
mayan/apps/acls/api_views.py
mayan/apps/acls/apps.py
mayan/apps/acls/classes.py
mayan/apps/acls/exceptions.py
mayan/apps/acls/links.py
mayan/apps/acls/managers.py
mayan/apps/acls/models.py
mayan/apps/acls/permissions.py
mayan/apps/acls/serializers.py
mayan/apps/acls/urls.py
mayan/apps/acls/views.py
mayan/apps/acls/workflow_actions.py
mayan/apps/acls/locale/ar/LC_MESSAGES/django.mo
mayan/apps/acls/locale/ar/LC_MESSAGES/django.po
mayan/apps/acls/locale/bg/LC_MESSAGES/django.mo
mayan/apps/acls/locale/bg/LC_MESSAGES/django.po
mayan/apps/acls/locale/bs_BA/LC_MESSAGES/django.mo
mayan/apps/acls/locale/bs_BA/LC_MESSAGES/django.po
mayan/apps/acls/locale/da/LC_MESSAGES/django.mo
mayan/apps/acls/locale/da/LC_MESSAGES/django.po
mayan/apps/acls/locale/de_DE/LC_MESSAGES/django.mo
mayan/apps/acls/locale/de_DE/LC_MESSAGES/django.po
mayan/apps/acls/locale/en/LC_MESSAGES/django.mo
mayan/apps/acls/locale/en/LC_MESSAGES/django.po
mayan/apps/acls/locale/es/LC_MESSAGES/django.mo
mayan/apps/acls/locale/es/LC_MESSAGES/django.po
mayan/apps/acls/locale/fa/LC_MESSAGES/django.mo
mayan/apps/acls/locale/fa/LC_MESSAGES/django.po
mayan/apps/acls/locale/fr/LC_MESSAGES/django.mo
mayan/apps/acls/locale/fr/LC_MESSAGES/django.po
mayan/apps/acls/locale/hu/LC_MESSAGES/django.mo
mayan/apps/acls/locale/hu/LC_MESSAGES/django.po
mayan/apps/acls/locale/id/LC_MESSAGES/django.mo
mayan/apps/acls/locale/id/LC_MESSAGES/django.po
mayan/apps/acls/locale/it/LC_MESSAGES/django.mo
mayan/apps/acls/locale/it/LC_MESSAGES/django.po
mayan/apps/acls/locale/nl_NL/LC_MESSAGES/django.mo
mayan/apps/acls/locale/nl_NL/LC_MESSAGES/django.po
mayan/apps/acls/locale/pl/LC_MESSAGES/django.mo
mayan/apps/acls/locale/pl/LC_MESSAGES/django.po
mayan_edms_ng.egg-info/PKG-INFO
mayan_edms_ng.egg-info/SOURCES.txt
mayan_edms_ng.egg-info/dependency_links.txt
mayan_edms_ng.egg-info/not-zip-safe
mayan_edms_ng.egg-info/requires.txt
mayan_edms_ng.egg-info/top_level.txt