Metadata-Version: 1.1
Name: mayan-edms-ng
Version: 2.8
Summary: Free Open Source Electronic Document Management System
Home-page: https://gitlab.com/mayan-edms/mayan-edms
Author: Roberto Rosario
Author-email: roberto.rosario@mayan-edms.com
License: Apache 2.0
Platform: any
Classifier: Development Status :: 5 - Production/Stable
Classifier: Environment :: Web Environment
Classifier: Framework :: Django
Classifier: Intended Audience :: Education
Classifier: Intended Audience :: Developers
Classifier: Intended Audience :: Information Technology
Classifier: License :: OSI Approved :: Apache Software License
Classifier: Natural Language :: English
Classifier: Programming Language :: Python
Classifier: Programming Language :: Python :: 2.7
Classifier: Topic :: Internet :: WWW/HTTP
Classifier: Topic :: Internet :: WWW/HTTP :: WSGI :: Application
Classifier: Topic :: Communications :: File Sharing
